glsr_present/__init__.py
glsr_present/__main__.py
glsr_present/commandline.py
glsr_present/static/report-parser-common.js
glsr_present/static/report.css
glsr_present/static/show-report.html
glsr_present/templates/build-info.md.j2
glsr_present-0.3.6.dist-info/LICENSE
glsr_present-0.3.6.dist-info/METADATA
glsr_present-0.3.6.dist-info/WHEEL
glsr_present-0.3.6.dist-info/entry_points.txt
glsr_present-0.3.6.dist-info/top_level.txt
glsr_present-0.3.6.dist-info/RECORD
