Metadata-Version: 2.1
Name: glsr-present
Version: 0.3.6
Summary: GitLab Security Reports Presenter
Author-email: Rainer Schwarzbach <undisclosed@example.com>
License: MIT License
Project-URL: Homepage, https://gitlab.com/blackstream-x/glsr-present
Project-URL: Documentation, https://blackstream-x.gitlab.io/glsr-present
Project-URL: CI, https://gitlab.com/blackstream-x/glsr-present/-/pipelines
Project-URL: Bug Tracker, https://gitlab.com/blackstream-x/glsr-present/-/issues
Project-URL: Repository, https://gitlab.com/blackstream-x/glsr-present.git
Keywords: gitlab-ci,security,reports,visualization
Classifier: Development Status :: 4 - Beta
Classifier: Environment :: Console
Classifier: Intended Audience :: Developers
Classifier: License :: OSI Approved :: MIT License
Classifier: Operating System :: OS Independent
Classifier: Programming Language :: Python :: 3
Classifier: Programming Language :: Python :: 3.8
Classifier: Programming Language :: Python :: 3.9
Classifier: Programming Language :: Python :: 3.10
Classifier: Programming Language :: Python :: 3.11
Classifier: Programming Language :: Python :: 3.12
Classifier: Programming Language :: Python :: 3.13
Classifier: Programming Language :: Python :: 3 :: Only
Classifier: Topic :: Software Development :: Documentation
Classifier: Topic :: Utilities
Requires-Python: >=3.8
License-File: LICENSE
Requires-Dist: Jinja2>=3.1.2
